bodhi/client/__init__.py
bodhi/client/bindings.py
bodhi/client/cli.py
bodhi/client/constants.py
bodhi/client/oidcclient.py
bodhi_client-25.11.3.dist-info/METADATA
bodhi_client-25.11.3.dist-info/WHEEL
bodhi_client-25.11.3.dist-info/entry_points.txt
bodhi_client-25.11.3.dist-info/licenses/COPYING
bodhi_client-25.11.3.dist-info/RECORD
